urbanaccess/__init__.py
urbanaccess/config.py
urbanaccess/gtfsfeeds.py
urbanaccess/network.py
urbanaccess/plot.py
urbanaccess/utils.py
urbanaccess/gtfs/__init__.py
urbanaccess/gtfs/gtfsfeeds_dataframe.py
urbanaccess/gtfs/headways.py
urbanaccess/gtfs/load.py
urbanaccess/gtfs/network.py
urbanaccess/gtfs/utils_format.py
urbanaccess/gtfs/utils_validation.py
urbanaccess/osm/__init__.py
urbanaccess/osm/load.py
urbanaccess/osm/network.py
urbanaccess-0.2.2.dist-info/METADATA
urbanaccess-0.2.2.dist-info/WHEEL
urbanaccess-0.2.2.dist-info/top_level.txt
urbanaccess-0.2.2.dist-info/RECORD
