Metadata-Version: 2.1
Name: urbanaccess
Version: 0.2.2
Summary: A tool for creating GTFS transit and OSM pedestrian networks for use in Pandana accessibility analyses.
Home-page: https://github.com/UDST/urbanaccess
Author: UrbanSim Inc. and Samuel D. Blanchard
Author-email: UNKNOWN
License: AGPL
Platform: UNKNOWN
Classifier: Programming Language :: Python :: 2
Classifier: Programming Language :: Python :: 2.7
Classifier: Programming Language :: Python :: 3
Classifier: Programming Language :: Python :: 3.5
Classifier: Programming Language :: Python :: 3.6
Classifier: Programming Language :: Python :: 3.7
Classifier: Programming Language :: Python :: 3.8
Classifier: Development Status :: 3 - Alpha
Classifier: License :: OSI Approved :: GNU Affero General Public License v3
Requires-Dist: requests (>=2.9.1)
Requires-Dist: six (>=1.11)
Requires-Dist: pandas (>=0.17.0)
Requires-Dist: numpy (>=1.11)
Requires-Dist: osmnet (>=0.1.4)
Requires-Dist: pandana (>=0.2.0)
Requires-Dist: matplotlib (>=2.0)
Requires-Dist: geopy (>=1.11.0)
Requires-Dist: pyyaml (>=3.11)
Requires-Dist: scikit-learn (>=0.17.1)
